reyfetch/__init__.py
reyfetch/rall.py
reyfetch/rbase.py
reyfetch/rbrowser.py
reyfetch/ritem/__init__.py
reyfetch/ritem/rali.py
reyfetch/ritem/rbaidu.py
reyfetch/ritem/rdouban.py
reyfetch/ritem/rgeneral.py
reyfetch/ritem/rsina.py
reyfetch/ritem/rtoutiao.py
reyfetch/ritem/rweibo.py
reyfetch-1.0.64.dist-info/METADATA
reyfetch-1.0.64.dist-info/WHEEL
reyfetch-1.0.64.dist-info/licenses/LICENSE
reyfetch-1.0.64.dist-info/RECORD
