Metadata-Version: 2.4
Name: reyfetch
Version: 1.0.64
Summary: Web data fetch method set.
Project-URL: homepage, https://github.com/reyxbo/reyfetch/
Author-email: Rey <reyxbo@163.com>
License: Copyright 2025 ReyXBo
License-File: LICENSE
Keywords: crawl Web,fetch,request API,rey,reyxbo
Requires-Python: >=3.12
Requires-Dist: bs4
Requires-Dist: fake-useragent
Requires-Dist: reydb
Requires-Dist: reykit
Requires-Dist: selenium
